spaceblocks_permissions_server/__init__.py
spaceblocks_permissions_server/api/__init__.py
spaceblocks_permissions_server/api/member_group_api.py
spaceblocks_permissions_server/api/permission_api.py
spaceblocks_permissions_server/api/resource_api.py
spaceblocks_permissions_server/api/role_api.py
spaceblocks_permissions_server/api/tenant_api.py
spaceblocks_permissions_server/api_client.py
spaceblocks_permissions_server/api_response.py
spaceblocks_permissions_server/configuration.py
spaceblocks_permissions_server/exceptions.py
spaceblocks_permissions_server/models/__init__.py
spaceblocks_permissions_server/models/create_member_group_request.py
spaceblocks_permissions_server/models/create_resource_parent.py
spaceblocks_permissions_server/models/create_resource_request.py
spaceblocks_permissions_server/models/create_role_request.py
spaceblocks_permissions_server/models/create_tenant_request.py
spaceblocks_permissions_server/models/get_permissions_response.py
spaceblocks_permissions_server/models/member_group.py
spaceblocks_permissions_server/models/problem_details.py
spaceblocks_permissions_server/models/resource.py
spaceblocks_permissions_server/models/resource_members.py
spaceblocks_permissions_server/models/resource_parent.py
spaceblocks_permissions_server/models/role.py
spaceblocks_permissions_server/models/tenant.py
spaceblocks_permissions_server/models/update_resource_parent.py
spaceblocks_permissions_server/models/update_resource_request.py
spaceblocks_permissions_server/models/update_role_request.py
spaceblocks_permissions_server/models/update_tenant_request.py
spaceblocks_permissions_server/permissions_client.py
spaceblocks_permissions_server/py.typed
spaceblocks_permissions_server/rest.py
spaceblocks_permissions_server-4.0.2.dist-info/METADATA
spaceblocks_permissions_server-4.0.2.dist-info/WHEEL
spaceblocks_permissions_server-4.0.2.dist-info/RECORD
