Metadata-Version: 2.1
Name: spaceblocks-permissions-server
Version: 4.0.2
Summary: Server SDK for Space Blocks Permissions, a permissions-as-a-service platform for developers
Home-page: https://spaceblocks.cloud
License: MIT
Keywords: space blocks,permissions,rbac
Author: Space Blocks Team
Author-email: hello@spaceblocks.cloud
Requires-Python: >=3.8,<4.0
Classifier: License :: OSI Approved :: MIT License
Classifier: Programming Language :: Python :: 3
Classifier: Programming Language :: Python :: 3.8
Classifier: Programming Language :: Python :: 3.9
Classifier: Programming Language :: Python :: 3.10
Classifier: Programming Language :: Python :: 3.11
Classifier: Programming Language :: Python :: 3.12
Requires-Dist: pydantic (>=2)
Requires-Dist: pyjwt (>=2.9.0,<3.0.0)
Requires-Dist: python-dateutil (>=2.8.2)
Requires-Dist: typing-extensions (>=4.7.1)
Requires-Dist: urllib3 (>=1.25.3)
Project-URL: Documentation, https://docs.spaceblocks.cloud/permissions
